[
    { "text": "Donald Duck’s middle name is Fauntelroy", "isTrue": true },
    {
      "text": "In the English language, it is never grammatically correct to start a sentence with 'because'.",
      "isTrue": false
    },
    { "text": "Bananas grow on trees.", "isTrue": false },
    {
      "text": "Lightning never strikes in the same place twice.",
      "isTrue": false
    },
    { "text": "Some cats are actually allergic to humans", "isTrue": true },
    {
      "text": "Approximately one quarter of human bones are in the feet",
      "isTrue": true
    },
    {
      "text": "There is actually a painting called 'Red Square', consisting of a plain red square.",
      "isTrue": true
    },
    {
      "text": "The total surface area of two human lungs is approximately 70 square metres",
      "isTrue": true
    },
    { "text": "An octopus has five hearts", "isTrue": false },
    {
      "text": "King Tutankhamun was one of the longest-ruling pharaohs of ancient Egypt.",
      "isTrue": false
    },
    {
      "text": "The chemical make up food often changes when you cook it.",
      "isTrue": true
    },
    {
      "text": "The Great Wall of China is longer than the distance between London and Beijing",
      "isTrue": true
    },
    {
      "text": " If you cry in space the tears just stick to your face.",
      "isTrue": true
    },
    {
      "text": "Coca Cola was first sold as a medicine for fatigue and headaches",
      "isTrue": true
    },
    { "text": "The word 'Quiz' also means an odd person.", "isTrue": true },
    {
      "text": "Flying in an aeroplane is statistically safer than driving in a car",
      "isTrue": true
    },
    {
      "text": "If you cut an earthworm in half, both halves can regrow their body.",
      "isTrue": false
    },
    {
      "text": "Buzz Aldrin's mother's maiden name was 'Moon'.",
      "isTrue": true
    },
    { "text": "A slug's blood is green", "isTrue": true },
    {
      "text": "Oxford University has been around longer than the Aztec Empire",
      "isTrue": true
    },
    { "text": " Sharks are mammals.", "isTrue": false },
    {
      "text": "Queen Elizabeth II is currently the second longest reigning British monarch",
      "isTrue": false
    },
    {
      "text": "Humans can distinguish between over a trillion different smells.",
      "isTrue": true
    },
    { "text": "The currency of France is the Franc", "isTrue": false },
    {
      "text": "There are more kangaroos in Australia than humans",
      "isTrue": true
    },
    {
      "text": "The Great Wall of China is visible from space",
      "isTrue": false
    },
    {
      "text": "Mosquitoes are considered to be the deadliest animals in the world",
      "isTrue": true
    },
    {
      "text": "NASA's computing power in 1969, when the USA sent men to the moon, is higher than today's smartphone.",
      "isTrue": false
    },
    {
      "text": "Uranus is tilted 98 degrees, so it appears to be lying on its side",
      "isTrue": true
    },
    { "text": "Marrakesh is the capital of Morocco", "isTrue": false },
    { "text": "Polar bears actually have white skin", "isTrue": false },
    {
      "text": "No piece of square dry paper can be folded in half more than 7 times",
      "isTrue": false
    },
    { "text": "Dinosaurs are older than dragonflies ", "isTrue": false },
    {
      "text": "You can lead a cow down stairs but not up stairs",
      "isTrue": false
    },
    {
      "text": "Your heartbeat stops for milliseconds when you sneeze",
      "isTrue": true
    },
    { "text": "Australia is wider than the moon", "isTrue": true },
    {
      "text": "Unlike fingerprints, tongue prints can be similar",
      "isTrue": false
    },
    { "text": "Monaco is the smallest country in the world", "isTrue": false },
    { "text": "Chocolates help in suppressing coughs", "isTrue": true },
    {
      "text": "Chocolate affects a dog's heart and nervous system; a few ounces are enough to kill a small dog",
      "isTrue": true
    },
    { "text": "A baker's dozen is 12", "isTrue": false },
    {
      "text": "The star sign Aquarius is represented by a tiger",
      "isTrue": true
    },
    { "text": "An emu can fly", "isTrue": false },
    { "text": "You're drinking water that dinosaurs drank.", "isTrue": true },
    { "text": "The Statue of Liberty was a gift from France", "isTrue": true },
    { "text": "Napoleon was of below-average height", "isTrue": false },
    {
      "text": "Okapis, the only living relative of giraffe, don't poop for the first time until they're one month old.",
      "isTrue": true
    },
    { "text": "Yawning is very contagious ", "isTrue": true },
    {
      "text": "Stephen Hawking declined a knighthood from the Queen",
      "isTrue": true
    },
    {
      "text": "'A' is the most common letter used in the English language",
      "isTrue": false
    }
  ]